[{"Id":12,"Title":"Quem Mexeu no Meu Queijo?","SubTitle":"Uma maneira fantástica de lidar com as mudanças em seu trabalho e em sua vida","Author":"Spencer Johnson","Cover":"http://img.skoob.com.br/livros_new/1/12/QUEM_MEXEU_NO_MEU_QUEIJO_1313524945Mini.jpg","Edition":69,"Publisher":"Record","ISBN10":"0","ISBN13":"0","Year":2010,"Pages":111,"Translators":"Maria Clara de Biase"},{"Id":12,"Title":"Quem Mexeu no Meu Queijo?","SubTitle":"Uma maneira fantástica de lidar com as mudanças em seu trabalho e em sua vida","Author":"Spencer Johnson","Cover":"http://img.skoob.com.br/livros_new/1/12/QUEM_MEXEU_NO_MEU_QUEIJO_1315924127Mini.jpg","Edition":67,"Publisher":"Record","ISBN10":"850105402X","ISBN13":"9788501054029","Year":2010,"Pages":107,"Translators":"Maria Clara de Biase"},{"Id":12,"Title":"Quem Mexeu no Meu Queijo?","SubTitle":"Uma maneira fantástica de lidar com as mudanças em seu trabalho e em sua vida","Author":"Spencer Johnson","Cover":"http://img.skoob.com.br/livros_new/1/12/QUEM_MEXEU_NO_MEU_QUEIJO_1291762917Mini.jpg","Edition":51,"Publisher":"Record","ISBN10":"850105402X","ISBN13":"9788501054029","Year":2006,"Pages":116,"Translators":"Maria Clara de Biase"},{"Id":12,"Title":"Quem Mexeu no Meu Queijo?","SubTitle":"Uma maneira fantástica de lidar com as mudanças em seu trabalho e em sua vida","Author":"Spencer Johnson","Cover":"http://img.skoob.com.br/livros_new/1/12/QUEM_MEXEU_NO_MEU_QUEIJO_1225842387Mini.jpg","Edition":43,"Publisher":"Record","ISBN10":"850105402X","ISBN13":"9788501054029","Year":2004,"Pages":107,"Translators":null},{"Id":12,"Title":"Quem Mexeu no Meu Queijo?","SubTitle":"Uma maneira fantástica de lidar com as mudanças em seu trabalho e em sua vida","Author":"Spencer Johnson","Cover":"http://img.skoob.com.br/livros_new/1/12/QUEM_MEXEU_NO_MEU_QUEIJO__1260908908Mini.jpg","Edition":40,"Publisher":"Record","ISBN10":"850105402x","ISBN13":"9788501054029","Year":2003,"Pages":107,"Translators":"Maria Clara de Biase"},{"Id":12,"Title":"Quem Mexeu no Meu Queijo?","SubTitle":"Uma maneira fantástica de lidar com as mudanças em seu trabalho e em sua vida","Author":"Spencer Johnson","Cover":"http://img.skoob.com.br/livros_new/1/12/QUEM_MEXEU_NO_MEU_QUEIJO_1290352762Mini.jpg","Edition":34,"Publisher":"Record","ISBN10":"850105402x","ISBN13":"9788501054029","Year":2002,"Pages":107,"Translators":"Maria Clara de Biase"},{"Id":12,"Title":"Quem Mexeu no Meu Queijo?","SubTitle":"Uma maneira fantástica de lidar com as mudanças em seu trabalho e em sua vida","Author":"Spencer Johnson","Cover":"http://img.skoob.com.br/livros_new/1/12/QUEM_MEXEU_NO_MEU_QUEIJO__1262734238Mini.jpg","Edition":2,"Publisher":"Record","ISBN10":"850105402X","ISBN13":"9788501054029","Year":1999,"Pages":91,"Translators":null}]